LICENSE
README.md
setup.py
data/__init__.py
data/dataset/__init__.py
samscore/__init__.py
samscore/samscore.py
samscore.egg-info/PKG-INFO
samscore.egg-info/SOURCES.txt
samscore.egg-info/dependency_links.txt
samscore.egg-info/requires.txt
samscore.egg-info/top_level.txt
util/__init__.py
util/html.py
util/util.py
util/visualizer.py