Metadata-Version: 2.1
Name: samscore
Version: 1.34
Summary: SAMScore Similarity Metric
Home-page: https://github.com/Kent0n-Li/SAMScore
Author: Yunxiang Li
Author-email: yunxiang.li@utsouthwestern.edu
License: UNKNOWN
Platform: UNKNOWN
Classifier: Programming Language :: Python :: 3
Classifier: License :: OSI Approved :: BSD License
Classifier: Operating System :: OS Independent
License-File: LICENSE
